.DS_Store
dp_table/__init__.py
dp_table/frontend/build/.DS_Store
dp_table/frontend/build/asset-manifest.json
dp_table/frontend/build/bootstrap.min.css
dp_table/frontend/build/index.html
dp_table/frontend/build/static/css/main.127fdcd1.css
dp_table/frontend/build/static/css/main.127fdcd1.css.map
dp_table/frontend/build/static/css/main.59363d86.css
dp_table/frontend/build/static/css/main.59363d86.css.map
dp_table/frontend/build/static/js/main.60cacada.js
dp_table/frontend/build/static/js/main.60cacada.js.LICENSE.txt
dp_table/frontend/build/static/js/main.60cacada.js.map
dp_table/frontend/build/static/js/main.6bdc8b0a.js
dp_table/frontend/build/static/js/main.6bdc8b0a.js.LICENSE.txt
dp_table/frontend/build/static/js/main.6bdc8b0a.js.map
dp_table/frontend/build/static/js/main.7030e8c7.js
dp_table/frontend/build/static/js/main.7030e8c7.js.LICENSE.txt
dp_table/frontend/build/static/js/main.7030e8c7.js.map
dp_table-0.0.4.dist-info/LICENSE
dp_table-0.0.4.dist-info/METADATA
dp_table-0.0.4.dist-info/WHEEL
dp_table-0.0.4.dist-info/top_level.txt
dp_table-0.0.4.dist-info/RECORD
